CONTRIBUTORS.txt
License.txt
MANIFEST.in
README.md
README.rst
TESTING.md
THANKS.txt
ez_setup.py
requirements.txt
setup.cfg
setup.py
test.sh
nexson/__init__.py
nexson/manip.py
nexson/proxy.py
nexson.egg-info/PKG-INFO
nexson.egg-info/SOURCES.txt
nexson.egg-info/dependency_links.txt
nexson.egg-info/entry_points.txt
nexson.egg-info/requires.txt
nexson.egg-info/top_level.txt
nexson.egg-info/zip-safe
nexson/syntax/__init__.py
nexson/syntax/badgerfish2direct_nexson.py
nexson/syntax/direct2badgerfish_nexson.py
nexson/syntax/direct2optimal_nexson.py
nexson/syntax/helper.py
nexson/syntax/inspect.py
nexson/syntax/nexml2nexson.py
nexson/syntax/nexson2nexml.py
nexson/syntax/optimal2direct_nexson.py
nexson/test/__init__.py
nexson/test/test_manip.py
nexson/test/test_merge_otus_and_trees.py
nexson/test/test_nexson_proxy_tree.py
nexson/test/test_nexson_syntax.py
nexson/test/test_nexson_validate_lacking_otus.py
nexson/test/test_nexson_validation.py
nexson/test/data/nexson/S15515.json
nexson/test/data/nexson/10/pg_10.json
nexson/test/data/nexson/9/nexml
nexson/test/data/nexson/9/phylografter_export.json
nexson/test/data/nexson/9/v0.0.json
nexson/test/data/nexson/9/v1.0.json
nexson/test/data/nexson/9/v1.2.json
nexson/test/data/nexson/invalid/bad_version.json.input
nexson/test/data/nexson/lacking_otus/ot_65.json.v0.0.input
nexson/test/data/nexson/lacking_otus/ot_65.json.v1.0.input
nexson/test/data/nexson/lacking_otus/ot_65.json.v1.2.input
nexson/test/data/nexson/merge/merge-expected.v1.0.json
nexson/test/data/nexson/merge/merge-expected.v1.2.json
nexson/test/data/nexson/merge/merge-input.v1.0.json
nexson/test/data/nexson/merge/merge-input.v1.2.json
nexson/test/data/nexson/old-tests/1003.json.v0.0.expected
nexson/test/data/nexson/old-tests/1003.json.v0.0.input
nexson/test/data/nexson/old-tests/124.nexson.v0.0.expected
nexson/test/data/nexson/old-tests/124.nexson.v0.0.input
nexson/test/data/nexson/old-tests/bogus-tag.nexson.v0.0.expected
nexson/test/data/nexson/old-tests/bogus-tag.nexson.v0.0.input
nexson/test/data/nexson/old-tests/bogus-tree-edge-source.nexson.v0.0.expected
nexson/test/data/nexson/old-tests/bogus-tree-edge-source.nexson.v0.0.input
